quam/__init__.py
quam/_version.py
quam/components/__init__.py
quam/components/basic_quam.py
quam/components/channels.py
quam/components/hardware.py
quam/components/octave.py
quam/components/pulses.py
quam/components/macro/__init__.py
quam/components/macro/qubit_macros.py
quam/components/macro/qubit_pair_macros.py
quam/components/ports/__init__.py
quam/components/ports/analog_inputs.py
quam/components/ports/analog_outputs.py
quam/components/ports/base_ports.py
quam/components/ports/digital_inputs.py
quam/components/ports/digital_outputs.py
quam/components/ports/ports_containers.py
quam/components/quantum_components/__init__.py
quam/components/quantum_components/quantum_component.py
quam/components/quantum_components/qubit.py
quam/components/quantum_components/qubit_pair.py
quam/config/__init__.py
quam/config/__main__.py
quam/config/resolvers.py
quam/config/validators.py
quam/config/vars.py
quam/config/cli/__init__.py
quam/config/cli/config.py
quam/config/cli/migrate.py
quam/config/cli/migrations/__init__.py
quam/config/cli/migrations/v1_v2.py
quam/config/models/__init__.py
quam/config/models/quam.py
quam/core/__init__.py
quam/core/deprecations.py
quam/core/qua_config_template.py
quam/core/quam_classes.py
quam/core/quam_instantiation.py
quam/core/macro/__init__.py
quam/core/macro/base_macro.py
quam/core/macro/method_macro.py
quam/core/macro/quam_macro.py
quam/core/operation/__init__.py
quam/core/operation/function_properties.py
quam/core/operation/operation.py
quam/core/operation/operations_registry.py
quam/examples/__init__.py
quam/examples/superconducting_qubits/__init__.py
quam/examples/superconducting_qubits/components.py
quam/examples/superconducting_qubits/cz_implementation.py
quam/examples/superconducting_qubits/generate_superconducting_quam.py
quam/examples/superconducting_qubits/operations.py
quam/serialisation/__init__.py
quam/serialisation/base.py
quam/serialisation/json.py
quam/utils/__init__.py
quam/utils/config.py
quam/utils/dataclass.py
quam-0.4.2.dist-info/licenses/LICENSE
quam-0.4.2.dist-info/METADATA
quam-0.4.2.dist-info/WHEEL
quam-0.4.2.dist-info/entry_points.txt
quam-0.4.2.dist-info/top_level.txt
quam-0.4.2.dist-info/RECORD
