Metadata-Version: 2.4
Name: quam
Version: 0.4.2
Summary: Quantum Abstract Machine (QUAM) facilitates development of abstraction layers in experiments.
Author-email: Serwan Asaad <serwan.asaad@quantum-machines.co>
License: BSD-3-Clause
Project-URL: Homepage, https://github.com/qua-platform/quam
Keywords: quantum-computing,experiment-control,quantum-infrastructure,abstraction-layer,abstraction-library
Classifier: Topic :: Scientific/Engineering
Classifier: Topic :: Scientific/Engineering :: Physics
Classifier: Topic :: Software Development
Classifier: Intended Audience :: Science/Research
Classifier: Intended Audience :: Information Technology
Classifier: Development Status :: 4 - Beta
Classifier: License :: OSI Approved :: BSD License
Requires-Python: <3.13,>=3.9
License-File: LICENSE
Requires-Dist: numpy>=1.21.2
Requires-Dist: qm-qua>=1.2.2
Requires-Dist: qualang-tools>=0.15.0
Requires-Dist: typeguard>=4.1.0
Requires-Dist: qualibrate-config>=0.1.6
Provides-Extra: dev
Requires-Dist: pytest>=7.1.2; extra == "dev"
Requires-Dist: black>=23.7.0; extra == "dev"
Requires-Dist: flake8>=5.0.1; extra == "dev"
Requires-Dist: pyproject-flake8>=5.0.0; extra == "dev"
Requires-Dist: ipykernel>=6.24.0; extra == "dev"
Requires-Dist: pytest-cov>=4.1.0; extra == "dev"
Requires-Dist: pytest-mock>=3.6.1; extra == "dev"
Provides-Extra: docs
Requires-Dist: mkdocstrings[python]>=0.18; extra == "docs"
Requires-Dist: mkdocs-gen-files; extra == "docs"
Requires-Dist: mkdocs-jupyter; extra == "docs"
Provides-Extra: build
Requires-Dist: setuptools>=71; extra == "build"
Requires-Dist: setuptools-scm>=8.1.0; extra == "build"
Requires-Dist: build>=1.2.1; extra == "build"
Dynamic: license-file
